mad_datasets/__init__.py
mad_datasets/egait_parameter_validation_2013/__init__.py
mad_datasets/egait_parameter_validation_2013/_dataset.py
mad_datasets/egait_parameter_validation_2013/helper.py
mad_datasets/egait_segmentation_validation_2014/__init__.py
mad_datasets/egait_segmentation_validation_2014/_dataset.py
mad_datasets/egait_segmentation_validation_2014/helper.py
mad_datasets/sensor_position_comparison_2019/__init__.py
mad_datasets/sensor_position_comparison_2019/_dataset.py
mad_datasets/sensor_position_comparison_2019/helper.py
mad_datasets/stair_ambulation_healthy_2021/__init__.py
mad_datasets/stair_ambulation_healthy_2021/_dataset.py
mad_datasets/stair_ambulation_healthy_2021/helper.py
mad_datasets/stair_ambulation_healthy_2021/pressure_sensor_helper.py
mad_datasets/stair_ambulation_healthy_2021/scripts/__init__.py
mad_datasets/stair_ambulation_healthy_2021/scripts/create_pressure_events.py
mad_datasets/utils/__init__.py
mad_datasets/utils/consts.py
mad_datasets/utils/coordinate_transforms.py
mad_datasets/utils/data_loading.py
mad_datasets/utils/egait_loading_helper.py
mad_datasets/utils/event_detection.py
mad_datasets-0.4.0.dist-info/METADATA
mad_datasets-0.4.0.dist-info/WHEEL
mad_datasets-0.4.0.dist-info/LICENSE
mad_datasets-0.4.0.dist-info/RECORD
