Metadata-Version: 2.1
Name: mad-datasets
Version: 0.4.0
Summary: Helper to access to open-source gait datasets used by MaD-Lab
Home-page: https://github.com/mad-lab-fau/mad-datasets
License: MIT
Author: Arne Küderle
Author-email: arne.kuederle@fau.de
Requires-Python: >=3.8,<4.0
Classifier: License :: OSI Approved :: MIT License
Classifier: Programming Language :: Python :: 3
Classifier: Programming Language :: Python :: 3.8
Classifier: Programming Language :: Python :: 3.9
Classifier: Programming Language :: Python :: 3.10
Classifier: Programming Language :: Python :: 3.11
Requires-Dist: c3d (>=0.5.1,<0.6.0)
Requires-Dist: imucal (>=2.3.0)
Requires-Dist: joblib (>=1.2.0)
Requires-Dist: nilspodlib (>=3.6.0)
Requires-Dist: pandas (>=1.4.2)
Requires-Dist: scipy (>=1.8.1)
Requires-Dist: tpcp (>=0.11)
Project-URL: Repository, https://github.com/mad-lab-fau/mad-datasets
